{"nodes": [{"id": "c_itbd_projects_m1trans_src_pages_index_tsx", "label": "Index.tsx", "file_type": "code", "source_file": "c:\\ITBD-projects\\m1trans\\src\\pages\\Index.tsx", "source_location": "L1"}, {"id": "index_index", "label": "Index()", "file_type": "code", "source_file": "c:\\ITBD-projects\\m1trans\\src\\pages\\Index.tsx", "source_location": "L4"}], "edges": [{"source": "c_itbd_projects_m1trans_src_pages_index_tsx", "target": "incidentreportform", "relation": "imports_from", "confidence": "EXTRACTED", "source_file": "c:\\ITBD-projects\\m1trans\\src\\pages\\Index.tsx", "source_location": "L1", "weight": 1.0}, {"source": "c_itbd_projects_m1trans_src_pages_index_tsx", "target": "lucide_react", "relation": "imports_from", "confidence": "EXTRACTED", "source_file": "c:\\ITBD-projects\\m1trans\\src\\pages\\Index.tsx", "source_location": "L2", "weight": 1.0}, {"source": "c_itbd_projects_m1trans_src_pages_index_tsx", "target": "index_index", "relation": "contains", "confidence": "EXTRACTED", "source_file": "c:\\ITBD-projects\\m1trans\\src\\pages\\Index.tsx", "source_location": "L4", "weight": 1.0}], "raw_calls": [{"caller_nid": "index_index", "callee": "getFullYear", "source_file": "c:\\ITBD-projects\\m1trans\\src\\pages\\Index.tsx", "source_location": "L32"}]}